magnus_extension_k8s_poller/implementation.py
magnus_extension_k8s_poller/integration.py
magnus_extension_k8s_poller-0.1.2.dist-info/entry_points.txt
magnus_extension_k8s_poller-0.1.2.dist-info/WHEEL
magnus_extension_k8s_poller-0.1.2.dist-info/METADATA
magnus_extension_k8s_poller-0.1.2.dist-info/RECORD
