Metadata-Version: 2.1
Name: magnus-extension-k8s-poller
Version: 0.1.2
Summary: Description you want to give
Home-page: https://github.com/AstraZeneca/magnus-extensions/
License: Apache-2.0
Author: Vijay Vammi
Author-email: vijay.vammi@astrazeneca.com
Requires-Python: >=3.7.1,<4.0.0
Classifier: License :: OSI Approved :: Apache Software License
Classifier: Programming Language :: Python :: 3
Classifier: Programming Language :: Python :: 3.10
Classifier: Programming Language :: Python :: 3.8
Classifier: Programming Language :: Python :: 3.9
Requires-Dist: kubernetes
Requires-Dist: magnus (>=0.3.12,<0.4.0)
Requires-Dist: magnus-extension-datastore-db (>=0.1.1,<0.2.0)
Requires-Dist: tqdm (>=4.64.0,<5.0.0)
Project-URL: Documentation, https://astrazeneca.github.io/magnus-extensions/
Project-URL: Repository, https://github.com/AstraZeneca/magnus-extensions/
